{
  "version": "1.0",
  "sector": "13",
  "channel_name": "T13_B_G3_BETA",
  "channel_id": 1,
  "mu_power": 2,
  "k_power_prefactor": 0,
  "radial_rank": 0,
  "symmetry": {
    "type": "none",
    "exchange_q_kmq": false
  },
  "master_family": "RADIAL_1D",
  "radial_kernel_type": "G3",
  "terms": [],
  "metadata": {
    "status": "radial-1d",
    "radial_kernel": "M13a_radial(nu) * M13b_G3(nu) = M13a(nu) * (-1/(1+nu))",
    "notes": "Standard SPT G3(q,-q,k) velocity-divergence kernel. The explicit mu^2 comes from the b_eta bias operator. Isotropic kernel, contributes only at mu^2. Mellin representation (CLASS-PT M13b index 4 convention).",
    "bias_contraction": "b_eta * f",
    "mu_powers": [2]
  }
}
